.gitignore
easy_3dgs-0.1.0.dist-info/METADATA
easy_3dgs-0.1.0.dist-info/WHEEL
easy_3dgs-0.1.0.dist-info/entry_points.txt
easy_3dgs-0.1.0.dist-info/licenses/LICENSE
easy_3dgs/__init__.py
easy_3dgs/pipeline/__init__.py
easy_3dgs/pipeline/feature_extraction/__init__.py
easy_3dgs/pipeline/feature_extraction/base.py
easy_3dgs/pipeline/feature_extraction/hloc_implementation.py
easy_3dgs/pipeline/feature_matching/__init__.py
easy_3dgs/pipeline/feature_matching/base.py
easy_3dgs/pipeline/feature_matching/hloc_implementation.py
easy_3dgs/pipeline/feature_retrieval/__init__.py
easy_3dgs/pipeline/feature_retrieval/base.py
easy_3dgs/pipeline/feature_retrieval/hloc_implementation.py
easy_3dgs/pipeline/image_undistortion/__init__.py
easy_3dgs/pipeline/image_undistortion/base.py
easy_3dgs/pipeline/image_undistortion/pycolmap_implementation.py
easy_3dgs/pipeline/orchestrator.py
easy_3dgs/pipeline/pair_generation/__init__.py
easy_3dgs/pipeline/pair_generation/base.py
easy_3dgs/pipeline/pair_generation/hloc_implementation.py
easy_3dgs/pipeline/reconstruction/__init__.py
easy_3dgs/pipeline/reconstruction/base.py
easy_3dgs/pipeline/reconstruction/hloc_implementation.py
easy_3dgs/py.typed
easy_3dgs-0.1.0.dist-info/RECORD
