Metadata-Version: 2.1
Name: easy-3dgs
Version: 0.1.0
Summary: A Python library that includes an end-to-end 3D Gaussian splatting pipeline without requiring the compilation of hundreds of dependencies.
Author-Email: jourdelune <jourdelune863@gmail.com>
Requires-Python: >=3.10
Requires-Dist: pycolmap>=3.11.1
